shortbread/__init__.py
shortbread/cli.py
shortbread/shortbread.py
shortbread-0.8.0.dist-info/AUTHORS.rst
shortbread-0.8.0.dist-info/LICENSE
shortbread-0.8.0.dist-info/METADATA
shortbread-0.8.0.dist-info/WHEEL
shortbread-0.8.0.dist-info/entry_points.txt
shortbread-0.8.0.dist-info/top_level.txt
shortbread-0.8.0.dist-info/RECORD
