Metadata-Version: 2.1
Name: shortbread
Version: 0.8.0
Summary: Shortbread recipe calculator.
Home-page: https://github.com/purplediane/shortbread
Author: Diane Chen
Author-email: dianedc@purpleweb.com
License: MIT license
Keywords: shortbread
Platform: UNKNOWN
Classifier: Development Status :: 3 - Alpha
Classifier: Intended Audience :: Developers
Classifier: Intended Audience :: End Users/Desktop
Classifier: License :: OSI Approved :: MIT License
Classifier: Natural Language :: English
Classifier: Programming Language :: Python :: 3.6
Classifier: Programming Language :: Python :: 3.7
Classifier: Programming Language :: Python :: 3.8
Requires-Dist: Click (>=6.0)
Requires-Dist: inflect (>=0.2.5)
